permmod/__init__.py
permmod/import_data.py
permmod/linear_system.py
permmod/measurement.py
permmod/optimize.py
permmod/plots.py
permmod-0.3.dist-info/METADATA
permmod-0.3.dist-info/WHEEL
permmod-0.3.dist-info/top_level.txt
permmod-0.3.dist-info/RECORD
