Metadata-Version: 2.1
Name: permmod
Version: 0.3
Summary: A package to calculate the permeability of rock samples
Author-email: Martin Kirch <mkirch@web.de>
Project-URL: Homepage, https://github.com/kirchma/permmod
Project-URL: Bug Tracker, https://github.com/kirchma/permmod/issues
Classifier: Programming Language :: Python :: 3
Classifier: License :: OSI Approved :: MIT License
Classifier: Operating System :: OS Independent
Requires-Python: >=3.11
Requires-Dist: pandas
Requires-Dist: numpy
Requires-Dist: CoolProp
Requires-Dist: scipy
Requires-Dist: plotly
